{
  "version": "1.0",
  "defaultProvider": "cdnjs",
  "libraries": [
    {
      "library": "fancybox@3.5.7",
      "destination": "wwwroot/lib/fancybox/"
    },
    {
      "library": "slick-carousel@1.8.1",
      "destination": "wwwroot/lib/slick-carousel/"
    },
    {
      "library": "font-awesome@5.15.4",
      "destination": "wwwroot/lib/font-awesome/"
    },
    {
      "library": "intl-tel-input@17.0.15",
      "destination": "wwwroot/lib/intl-tel-input/"
    },
    {
      "library": "bootstrap-select@1.13.18",
      "destination": "wwwroot/lib/bootstrap-select/"
    }
  ]
}